reframed/__init__.py
reframed/alpha/__init__.py
reframed/alpha/fluxutils.py
reframed/alpha/gapMake.py
reframed/alpha/geneswitch.py
reframed/alpha/plotting.py
reframed/alpha/sampling.py
reframed/cli/__init__.py
reframed/cli/cli.py
reframed/cobra/__init__.py
reframed/cobra/auxotrophy.py
reframed/cobra/ensemble.py
reframed/cobra/knockout.py
reframed/cobra/medium.py
reframed/cobra/plotting.py
reframed/cobra/simulation.py
reframed/cobra/thermodynamics.py
reframed/cobra/transcriptomics.py
reframed/cobra/variability.py
reframed/community/SteadyCom.py
reframed/community/__init__.py
reframed/community/model.py
reframed/community/solution.py
reframed/core/__init__.py
reframed/core/cbmodel.py
reframed/core/elements.py
reframed/core/environment.py
reframed/core/model.py
reframed/core/parser.py
reframed/core/transformation.py
reframed/external/__init__.py
reframed/external/cobrapy.py
reframed/external/escher.py
reframed/io/__init__.py
reframed/io/cache.py
reframed/io/sbml.py
reframed/solvers/__init__.py
reframed/solvers/cplex_solver.py
reframed/solvers/gurobi_solver.py
reframed/solvers/scip_solver.py
reframed/solvers/solution.py
reframed/solvers/solver.py
reframed-1.6.0.dist-info/licenses/LICENSE
tests/__init__.py
tests/scip_carveme.py
tests/test_reframed.py
tests/data/e_coli_core.xml.gz
tests/data/iML1515.xml.gz
tests/data/model_cobra.xml.gz
tests/data/model_fbc2.xml.gz
reframed-1.6.0.dist-info/METADATA
reframed-1.6.0.dist-info/WHEEL
reframed-1.6.0.dist-info/entry_points.txt
reframed-1.6.0.dist-info/top_level.txt
reframed-1.6.0.dist-info/RECORD
