Metadata-Version: 2.4
Name: reframed
Version: 1.6.0
Summary: metabolic modeling package
Home-page: https://github.com/cdanielmachado/reframed
Author: Daniel Machado
Author-email: cdanielmachado@gmail.com
License: Apache Software License 2.0
Keywords: reframed
Classifier: License :: OSI Approved :: Apache Software License
Classifier: Programming Language :: Python :: 3.8
Classifier: Programming Language :: Python :: 3.9
Classifier: Programming Language :: Python :: 3.10
Classifier: Programming Language :: Python :: 3.11
Classifier: Programming Language :: Python :: 3.12
Classifier: Programming Language :: Python :: 3.13
Requires-Python: >=3.8
License-File: LICENSE
Requires-Dist: numpy
Requires-Dist: scipy
Requires-Dist: sympy
Requires-Dist: python-libsbml
Requires-Dist: pyscipopt
Dynamic: author
Dynamic: author-email
Dynamic: classifier
Dynamic: description
Dynamic: home-page
Dynamic: keywords
Dynamic: license
Dynamic: license-file
Dynamic: requires-dist
Dynamic: requires-python
Dynamic: summary
